{
  "events": [
    {
      "id": "EVENT-01",
      "title": "Baseball Game: Cal State Bakersfield Roadrunners at California Golden Bears",
      "organizer": "California Golden Bears Athletics",
      "date": "2026-03-04",
      "time": "6:05 PM",
      "location": "Evans Diamond at Stu Gordon Stadium, Berkeley, CA",
      "description": "UC Berkeley's baseball team plays against Cal State Bakersfield in a home game.",
      "url": "https://calbears.com/calendar",
      "tags": [
        "Sports"
      ]
    },
    {
      "id": "EVENT-02",
      "title": "Baseball Game: San Diego Toreros at California Golden Bears",
      "organizer": "California Golden Bears Athletics",
      "date": "2026-03-06",
      "time": "6:05 PM",
      "location": "Evans Diamond at Stu Gordon Stadium, Berkeley, CA",
      "description": "UC Berkeley's baseball team plays against San Diego in a home game.",
      "url": "https://calbears.com/calendar",
      "tags": [
        "Sports"
      ]
    },
    {
      "id": "EVENT-03",
      "title": "Baseball Game: San Diego Toreros at California Golden Bears (Game 1 of DH)",
      "organizer": "California Golden Bears Athletics",
      "date": "2026-03-07",
      "time": "1:05 PM",
      "location": "Evans Diamond at Stu Gordon Stadium, Berkeley, CA",
      "description": "UC Berkeley's baseball team plays against San Diego in the first game of a doubleheader.",
      "url": "https://calbears.com/calendar",
      "tags": [
        "Sports"
      ]
    },
    {
      "id": "EVENT-04",
      "title": "Baseball Game: San Diego Toreros at California Golden Bears (Game 2 of DH)",
      "organizer": "California Golden Bears Athletics",
      "date": "2026-03-07",
      "time": "5:05 PM",
      "location": "Evans Diamond at Stu Gordon Stadium, Berkeley, CA",
      "description": "UC Berkeley's baseball team plays against San Diego in the second game of a doubleheader.",
      "url": "https://calbears.com/calendar",
      "tags": [
        "Sports"
      ]
    },
    {
      "id": "EVENT-05",
      "title": "Baseball Game: San Diego Toreros at California Golden Bears",
      "organizer": "California Golden Bears Athletics",
      "date": "2026-03-08",
      "time": "1:05 PM",
      "location": "Evans Diamond at Stu Gordon Stadium, Berkeley, CA",
      "description": "UC Berkeley's baseball team plays against San Diego in a home game.",
      "url": "https://calbears.com/calendar",
      "tags": [
        "Sports"
      ]
    },
    {
      "id": "EVENT-06",
      "title": "International Conference on Machine Learning and Chat GPT (ICMLCG)",
      "organizer": "Conference Organizer (Berkeley-based)",
      "date": "2026-03-09",
      "time": "TBD",
      "location": "Berkeley, California, USA",
      "description": "An international conference on advancements in machine learning and conversational AI.",
      "url": "https://events.berkeley.edu/",
      "tags": [
        "Academic",
        "Science & Tech"
      ]
    },
    {
      "id": "EVENT-07",
      "title": "Career Counseling 1:1's Drop Ins",
      "organizer": "UC Berkeley Graduate Division",
      "date": "2026-03-10",
      "time": "11:30 AM – 12:30 PM",
      "location": "UC Berkeley Campus",
      "description": "Drop-in career counseling sessions for graduate students to discuss their career paths.",
      "url": "https://grad.berkeley.edu/events/",
      "tags": [
        "Student Life"
      ]
    },
    {
      "id": "EVENT-08",
      "title": "AIGP Presents: Spring Indigenous Grad Student Ceramic Workshop",
      "organizer": "UC Berkeley Graduate Division / AIGP",
      "date": "2026-03-10",
      "time": "1:00 PM – 3:00 PM",
      "location": "UC Berkeley Campus",
      "description": "A ceramic workshop for Indigenous graduate students, fostering community and creativity.",
      "url": "https://grad.berkeley.edu/events/",
      "tags": [
        "Arts",
        "Student Life"
      ]
    },
    {
      "id": "EVENT-09",
      "title": "Baseball Game: North Carolina Tar Heels at California Golden Bears",
      "organizer": "California Golden Bears Athletics",
      "date": "2026-03-13",
      "time": "6:05 PM",
      "location": "Evans Diamond at Stu Gordon Stadium, Berkeley, CA",
      "description": "UC Berkeley's baseball team plays against North Carolina.",
      "url": "https://calbears.com/calendar",
      "tags": [
        "Sports"
      ]
    },
    {
      "id": "EVENT-10",
      "title": "Baseball Game: North Carolina Tar Heels at California Golden Bears",
      "organizer": "California Golden Bears Athletics",
      "date": "2026-03-14",
      "time": "2:05 PM",
      "location": "Evans Diamond at Stu Gordon Stadium, Berkeley, CA",
      "description": "UC Berkeley's baseball team plays against North Carolina.",
      "url": "https://calbears.com/calendar",
      "tags": [
        "Sports"
      ]
    },
    {
      "id": "EVENT-11",
      "title": "Baseball Game: North Carolina Tar Heels at California Golden Bears",
      "organizer": "California Golden Bears Athletics",
      "date": "2026-03-15",
      "time": "1:05 PM",
      "location": "Evans Diamond at Stu Gordon Stadium, Berkeley, CA",
      "description": "UC Berkeley's baseball team plays against North Carolina.",
      "url": "https://calbears.com/calendar",
      "tags": [
        "Sports"
      ]
    },
    {
      "id": "EVENT-12",
      "title": "Baseball Game: TBD Opponent at California Golden Bears",
      "organizer": "California Golden Bears Athletics",
      "date": "2026-03-17",
      "time": "6:05 PM",
      "location": "Evans Diamond at Stu Gordon Stadium, Berkeley, CA",
      "description": "UC Berkeley's baseball team in a non-conference home game.",
      "url": "https://calbears.com/calendar",
      "tags": [
        "Sports"
      ]
    },
    {
      "id": "EVENT-13",
      "title": "Cal Invitational (Track & Field)",
      "organizer": "California Golden Bears Athletics",
      "date": "2026-03-21",
      "time": "TBD",
      "location": "Edwards Stadium, Berkeley, CA",
      "description": "UC Berkeley hosts its annual Track & Field invitational, serving as the outdoor opener for the season.",
      "url": "https://calbears.com/calendar",
      "tags": [
        "Sports"
      ]
    },
    {
      "id": "EVENT-14",
      "title": "Baseball Game: TBD Opponent at California Golden Bears",
      "organizer": "California Golden Bears Athletics",
      "date": "2026-03-31",
      "time": "6:05 PM",
      "location": "Evans Diamond at Stu Gordon Stadium, Berkeley, CA",
      "description": "UC Berkeley's baseball team in a non-conference home game.",
      "url": "https://calbears.com/calendar",
      "tags": [
        "Sports"
      ]
    },
    {
      "id": "EVENT-15",
      "title": "Coffee with Grad Div at the Gate",
      "organizer": "UC Berkeley Graduate Division",
      "date": "2026-04-01",
      "time": "10:00 AM",
      "location": "Sather Gate, UC Berkeley",
      "description": "Free coffee and treats provided by the Graduate Division for students at Sather Gate.",
      "url": "https://grad.berkeley.edu/events/coffee-with-grad-div-at-the-gate",
      "tags": [
        "Student Life"
      ]
    },
    {
      "id": "EVENT-16",
      "title": "Brutus Hamilton Multi-Events (Track & Field Day 1)",
      "organizer": "California Golden Bears Athletics",
      "date": "2026-04-02",
      "time": "11:30 AM",
      "location": "Edwards Stadium, Berkeley, CA",
      "description": "Day 1 of the multi-events competition hosted by Cal Track & Field.",
      "url": "https://calbears.com/calendar",
      "tags": [
        "Sports"
      ]
    },
    {
      "id": "EVENT-17",
      "title": "Baseball Game: TBD Opponent at California Golden Bears",
      "organizer": "California Golden Bears Athletics",
      "date": "2026-04-02",
      "time": "6:05 PM",
      "location": "Evans Diamond at Stu Gordon Stadium, Berkeley, CA",
      "description": "UC Berkeley's baseball team in a conference home game.",
      "url": "https://calbears.com/calendar",
      "tags": [
        "Sports"
      ]
    },
    {
      "id": "EVENT-18",
      "title": "International Conference on Big Data Computer Science and Information (ICBDCSI)",
      "organizer": "Conference Organizer (Berkeley-based)",
      "date": "2026-04-02",
      "time": "TBD",
      "location": "Berkeley, California, USA",
      "description": "A conference focusing on big data, computer science, and information technology.",
      "url": "https://events.berkeley.edu/",
      "tags": [
        "Academic",
        "Science & Tech"
      ]
    },
    {
      "id": "EVENT-19",
      "title": "Brutus Hamilton Multi-Events (Track & Field Day 2)",
      "organizer": "California Golden Bears Athletics",
      "date": "2026-04-03",
      "time": "11:00 AM",
      "location": "Edwards Stadium, Berkeley, CA",
      "description": "Day 2 of the multi-events competition hosted by Cal Track & Field.",
      "url": "https://calbears.com/calendar",
      "tags": [
        "Sports"
      ]
    },
    {
      "id": "EVENT-20",
      "title": "Baseball Game: TBD Opponent at California Golden Bears",
      "organizer": "California Golden Bears Athletics",
      "date": "2026-04-03",
      "time": "6:05 PM",
      "location": "Evans Diamond at Stu Gordon Stadium, Berkeley, CA",
      "description": "UC Berkeley's baseball team in a conference home game.",
      "url": "https://calbears.com/calendar",
      "tags": [
        "Sports"
      ]
    },
    {
      "id": "EVENT-21",
      "title": "Brutus Hamilton Invitational (Track & Field)",
      "organizer": "California Golden Bears Athletics",
      "date": "2026-04-04",
      "time": "TBD",
      "location": "Edwards Stadium, Berkeley, CA",
      "description": "The Brutus Hamilton Invitational, also serving as the Bears' Senior Day for track and field athletes.",
      "url": "https://calbears.com/calendar",
      "tags": [
        "Sports"
      ]
    },
    {
      "id": "EVENT-22",
      "title": "Baseball Game: TBD Opponent at California Golden Bears",
      "organizer": "California Golden Bears Athletics",
      "date": "2026-04-04",
      "time": "1:05 PM",
      "location": "Evans Diamond at Stu Gordon Stadium, Berkeley, CA",
      "description": "UC Berkeley's baseball team in a conference home game.",
      "url": "https://calbears.com/calendar",
      "tags": [
        "Sports"
      ]
    },
    {
      "id": "EVENT-23",
      "title": "2026 BioEHSC, A Bioengineering High School Competition",
      "organizer": "University of California, Berkeley",
      "date": "2026-04-04",
      "time": "8:30 AM",
      "location": "University of California, Berkeley",
      "description": "A bioengineering competition for high school students, hosted at UC Berkeley.",
      "url": "https://www.eventbrite.com/d/united-states--berkeley-ca/science-tech--events/",
      "tags": [
        "Science & Tech",
        "Academic"
      ]
    },
    {
      "id": "EVENT-24",
      "title": "Baseball Game: TBD Opponent at California Golden Bears",
      "organizer": "California Golden Bears Athletics",
      "date": "2026-04-06",
      "time": "2:00 PM",
      "location": "Evans Diamond at Stu Gordon Stadium, Berkeley, CA",
      "description": "UC Berkeley's baseball team in a non-conference home game.",
      "url": "https://calbears.com/calendar",
      "tags": [
        "Sports"
      ]
    },
    {
      "id": "EVENT-25",
      "title": "Grad Slam Campus-wide Competition",
      "organizer": "UC Berkeley Graduate Division",
      "date": "2026-04-08",
      "time": "3:00 PM – 5:30 PM",
      "location": "Banatao Auditorium, Sutardja Dai Hall, Berkeley, CA",
      "description": "Graduate students present their research in compelling three-minute talks, competing for campus prizes.",
      "url": "https://events.berkeley.edu/",
      "tags": [
        "Academic",
        "Student Life"
      ]
    },
    {
      "id": "EVENT-26",
      "title": "ISQED'26 - General Registration (International Symposium on Quality Electronic Design)",
      "organizer": "Symposium Organizer (Berkeley-based)",
      "date": "2026-04-08",
      "time": "8:30 AM",
      "location": "Seven Hills Conference Center, Berkeley, CA",
      "description": "General registration for the International Symposium on Quality Electronic Design, a prominent academic event.",
      "url": "https://www.eventbrite.com/d/united-states--berkeley-ca/science-tech--events/",
      "tags": [
        "Academic",
        "Science & Tech"
      ]
    },
    {
      "id": "EVENT-27",
      "title": "Baseball Game: TBD Opponent at California Golden Bears",
      "organizer": "California Golden Bears Athletics",
      "date": "2026-04-15",
      "time": "6:05 PM",
      "location": "Evans Diamond at Stu Gordon Stadium, Berkeley, CA",
      "description": "UC Berkeley's baseball team in a conference home game.",
      "url": "https://calbears.com/calendar",
      "tags": [
        "Sports"
      ]
    },
    {
      "id": "EVENT-28",
      "title": "EECS Cal Day: EECS Advisor Tabling",
      "organizer": "UC Berkeley EECS Department",
      "date": "2026-04-18",
      "time": "TBD",
      "location": "Engineering Information Zone, UC Berkeley",
      "description": "Meet Electrical Engineering and Computer Science advisors to learn about academic programs and opportunities.",
      "url": "https://events.berkeley.edu/",
      "tags": [
        "Academic",
        "Science & Tech",
        "Student Life"
      ]
    },
    {
      "id": "EVENT-29",
      "title": "EECS Cal Day: CS Advisor Tabling",
      "organizer": "UC Berkeley EECS Department",
      "date": "2026-04-18",
      "time": "TBD",
      "location": "Northwest Information Zone, UC Berkeley",
      "description": "Meet Computer Science advisors to learn about academic programs and opportunities.",
      "url": "https://events.berkeley.edu/",
      "tags": [
        "Academic",
        "Science & Tech",
        "Student Life"
      ]
    },
    {
      "id": "EVENT-30",
      "title": "EECS Cal Day: Tours of Soda and Cory Halls",
      "organizer": "UC Berkeley EECS Department",
      "date": "2026-04-18",
      "time": "Tours depart every 30 minutes",
      "location": "3rd floor lobby, Soda Hall, UC Berkeley",
      "description": "Guided tours showcasing the facilities of the Electrical Engineering and Computer Sciences department.",
      "url": "https://events.berkeley.edu/",
      "tags": [
        "Academic",
        "Science & Tech",
        "Student Life"
      ]
    },
    {
      "id": "EVENT-31",
      "title": "EECS Cal Day: Kickstarting Your Journey as a Woman in CS!",
      "organizer": "UC Berkeley EECS Department",
      "date": "2026-04-18",
      "time": "TBD",
      "location": "UC Berkeley",
      "description": "An event for female-identifying prospective students interested in Computer Science, featuring a bootcamp and alumni discussions.",
      "url": "https://events.berkeley.edu/",
      "tags": [
        "Science & Tech",
        "Student Life"
      ]
    },
    {
      "id": "EVENT-32",
      "title": "EECS Cal Day: Women in Tech Panel and Lunch with AWE",
      "organizer": "Association of Women in Electrical Engineering and Computer Science (AWE)",
      "date": "2026-04-18",
      "time": "TBD",
      "location": "UC Berkeley",
      "description": "A panel discussion and lunch for admitted students to learn about being a Berkeley CS/EECS student.",
      "url": "https://events.berkeley.edu/",
      "tags": [
        "Science & Tech",
        "Student Life"
      ]
    },
    {
      "id": "EVENT-33",
      "title": "EECS Cal Day: Computer Science Upper-Division Showcase",
      "organizer": "UC Berkeley EECS Department",
      "date": "2026-04-18",
      "time": "TBD",
      "location": "UC Berkeley",
      "description": "Overview of upper-division Computer Science course offerings, research opportunities, and career paths.",
      "url": "https://events.berkeley.edu/",
      "tags": [
        "Academic",
        "Science & Tech",
        "Student Life"
      ]
    },
    {
      "id": "EVENT-34",
      "title": "BETR/EECS Solid State Technologies Seminar: Dr. Emma Rosenfeld, Google Quantum AI",
      "organizer": "UC Berkeley EECS Department / BETR",
      "date": "2026-04-24",
      "time": "4:00 PM – 5:00 PM",
      "location": "Banatao Auditorium, 310 Sutardja Dai Hall Berkeley, CA",
      "description": "A seminar on magic state cultivation on a superconducting quantum processor by Dr. Emma Rosenfeld.",
      "url": "https://events.berkeley.edu/",
      "tags": [
        "Academic",
        "Science & Tech"
      ]
    },
    {
      "id": "EVENT-35",
      "title": "2026 California Neurotechnology Conference",
      "organizer": "UC Berkeley affiliated",
      "date": "2026-04-26",
      "time": "8:00 AM",
      "location": "International House at UC Berkeley",
      "description": "A conference focusing on neurotechnology research and innovations hosted at UC Berkeley.",
      "url": "https://www.eventbrite.com/d/united-states--berkeley-ca/science-tech--events/",
      "tags": [
        "Science & Tech",
        "Academic"
      ]
    },
    {
      "id": "EVENT-36",
      "title": "International Conference on Big Data and Data Science (ICBDS)",
      "organizer": "Conference Organizer (Berkeley-based)",
      "date": "2026-05-02",
      "time": "TBD",
      "location": "Berkeley, California, USA",
      "description": "An international conference on advancements in big data and data science.",
      "url": "https://events.berkeley.edu/",
      "tags": [
        "Academic",
        "Science & Tech"
      ]
    },
    {
      "id": "EVENT-37",
      "title": "2026 First Generation End of Year Celebration",
      "organizer": "UC Berkeley Graduate Division",
      "date": "2026-05-14",
      "time": "12:00 PM - 2:00 PM",
      "location": "The Inclusive Excellence Hub, 2515 Channing Way Berkeley, CA",
      "description": "A celebration for first-generation graduate students, faculty, staff, and allies to mark the end of the academic year.",
      "url": "https://grad.berkeley.edu/events/2026-first-generation-end-of-year-celebration",
      "tags": [
        "Student Life"
      ]
    },
    {
      "id": "EVENT-38",
      "title": "International Conference on Big Data, IoT and Machine Learning (ICBIoTML)",
      "organizer": "Conference Organizer (Berkeley-based)",
      "date": "2026-05-25",
      "time": "TBD",
      "location": "Berkeley, California, USA",
      "description": "A conference exploring the convergence of big data, IoT, and machine learning technologies.",
      "url": "https://events.berkeley.edu/",
      "tags": [
        "Academic",
        "Science & Tech"
      ]
    },
    {
      "id": "EVENT-39",
      "title": "Revisiting Indirect Land Use Change in Biofuel Policies",
      "organizer": "UC Berkeley (implied)",
      "date": "2026-05-28",
      "time": "8:00 AM",
      "location": "Wells Fargo Room, UC Berkeley, Berkeley, CA",
      "description": "A discussion or seminar on the policy implications of indirect land use change related to biofuels.",
      "url": "https://www.eventbrite.com/d/united-states--berkeley-ca/science-tech--events/",
      "tags": [
        "Academic",
        "Science & Tech"
      ]
    },
    {
      "id": "EHUB_20260305_025",
      "title": "Startup Group Therapy (Members-only)",
      "organizer": "Berkeley E-Hub",
      "date": "2026-03-05",
      "time": "See event page",
      "location": "Berkeley E-Hub",
      "description": "Startup Group Therapy (Members-only)",
      "url": "https://ehub.berkeley.edu/events/",
      "tags": [
        "Entrepreneurship"
      ]
    },
    {
      "id": "EHUB_20260305_017",
      "title": "Problem of the Month: Framing the Problem",
      "organizer": "Berkeley E-Hub",
      "date": "2026-03-05",
      "time": "See event page",
      "location": "Berkeley E-Hub",
      "description": "Problem of the Month: Framing the Problem",
      "url": "https://ehub.berkeley.edu/events/",
      "tags": [
        "Entrepreneurship"
      ]
    },
    {
      "id": "EHUB_20260310_026",
      "title": "Startup Group Therapy (Members-only)",
      "organizer": "Berkeley E-Hub",
      "date": "2026-03-10",
      "time": "See event page",
      "location": "Berkeley E-Hub",
      "description": "Startup Group Therapy (Members-only)",
      "url": "https://ehub.berkeley.edu/events/",
      "tags": [
        "Entrepreneurship"
      ]
    },
    {
      "id": "EHUB_20260312_018",
      "title": "Problem of the Month: Empathy & Ideation",
      "organizer": "Berkeley E-Hub",
      "date": "2026-03-12",
      "time": "See event page",
      "location": "Berkeley E-Hub",
      "description": "Problem of the Month: Empathy & Ideation",
      "url": "https://ehub.berkeley.edu/events/",
      "tags": [
        "Entrepreneurship"
      ]
    },
    {
      "id": "EHUB_20260317_027",
      "title": "Startup Group Therapy (Members-only)",
      "organizer": "Berkeley E-Hub",
      "date": "2026-03-17",
      "time": "See event page",
      "location": "Berkeley E-Hub",
      "description": "Startup Group Therapy (Members-only)",
      "url": "https://ehub.berkeley.edu/events/",
      "tags": [
        "Entrepreneurship"
      ]
    },
    {
      "id": "EHUB_20260318_019",
      "title": "Real Work, Real Conversations",
      "organizer": "Berkeley E-Hub",
      "date": "2026-03-18",
      "time": "See event page",
      "location": "Berkeley E-Hub",
      "description": "Real Work, Real Conversations",
      "url": "https://ehub.berkeley.edu/events/",
      "tags": [
        "Entrepreneurship"
      ]
    },
    {
      "id": "EHUB_20260319_020",
      "title": "Problem of the Month: From Ideas to Experiments",
      "organizer": "Berkeley E-Hub",
      "date": "2026-03-19",
      "time": "See event page",
      "location": "Berkeley E-Hub",
      "description": "Problem of the Month: From Ideas to Experiments",
      "url": "https://ehub.berkeley.edu/events/",
      "tags": [
        "Entrepreneurship"
      ]
    },
    {
      "id": "EHUB_20260401_028",
      "title": "Startup Group Therapy (Members-only)",
      "organizer": "Berkeley E-Hub",
      "date": "2026-04-01",
      "time": "See event page",
      "location": "Berkeley E-Hub",
      "description": "Startup Group Therapy (Members-only)",
      "url": "https://ehub.berkeley.edu/events/",
      "tags": [
        "Entrepreneurship"
      ]
    },
    {
      "id": "EHUB_20260402_021",
      "title": "Outside Your Comfort Zone",
      "organizer": "Berkeley E-Hub",
      "date": "2026-04-02",
      "time": "See event page",
      "location": "Berkeley E-Hub",
      "description": "Outside Your Comfort Zone",
      "url": "https://ehub.berkeley.edu/events/",
      "tags": [
        "Entrepreneurship"
      ]
    },
    {
      "id": "EHUB_20260408_029",
      "title": "Startup Group Therapy (Members-only)",
      "organizer": "Berkeley E-Hub",
      "date": "2026-04-08",
      "time": "See event page",
      "location": "Berkeley E-Hub",
      "description": "Startup Group Therapy (Members-only)",
      "url": "https://ehub.berkeley.edu/events/",
      "tags": [
        "Entrepreneurship"
      ]
    },
    {
      "id": "EHUB_20260409_022",
      "title": "Problem of the Month: Framing the Problem",
      "organizer": "Berkeley E-Hub",
      "date": "2026-04-09",
      "time": "See event page",
      "location": "Berkeley E-Hub",
      "description": "Problem of the Month: Framing the Problem",
      "url": "https://ehub.berkeley.edu/events/",
      "tags": [
        "Entrepreneurship"
      ]
    },
    {
      "id": "EHUB_20260415_023",
      "title": "Real Work, Real Conversations",
      "organizer": "Berkeley E-Hub",
      "date": "2026-04-15",
      "time": "See event page",
      "location": "Berkeley E-Hub",
      "description": "Real Work, Real Conversations",
      "url": "https://ehub.berkeley.edu/events/",
      "tags": [
        "Entrepreneurship"
      ]
    },
    {
      "id": "EHUB_20260416_030",
      "title": "Startup Group Therapy (Members-only)",
      "organizer": "Berkeley E-Hub",
      "date": "2026-04-16",
      "time": "See event page",
      "location": "Berkeley E-Hub",
      "description": "Startup Group Therapy (Members-only)",
      "url": "https://ehub.berkeley.edu/events/",
      "tags": [
        "Entrepreneurship"
      ]
    },
    {
      "id": "EHUB_20260416_024",
      "title": "Problem of the Month: Empathy & Ideation",
      "organizer": "Berkeley E-Hub",
      "date": "2026-04-16",
      "time": "See event page",
      "location": "Berkeley E-Hub",
      "description": "Problem of the Month: Empathy & Ideation",
      "url": "https://ehub.berkeley.edu/events/",
      "tags": [
        "Entrepreneurship"
      ]
    },
    {
      "id": "EHUB_20260422_031",
      "title": "Startup Group Therapy (Members-only)",
      "organizer": "Berkeley E-Hub",
      "date": "2026-04-22",
      "time": "See event page",
      "location": "Berkeley E-Hub",
      "description": "Startup Group Therapy (Members-only)",
      "url": "https://ehub.berkeley.edu/events/",
      "tags": [
        "Entrepreneurship"
      ]
    },
    {
      "id": "EHUB_20260429_032",
      "title": "Startup Group Therapy (Members-only)",
      "organizer": "Berkeley E-Hub",
      "date": "2026-04-29",
      "time": "See event page",
      "location": "Berkeley E-Hub",
      "description": "Startup Group Therapy (Members-only)",
      "url": "https://ehub.berkeley.edu/events/",
      "tags": [
        "Entrepreneurship"
      ]
    },
    {
      "id": "EHUB_20260827_033",
      "title": "Start Something @ the eHub Open House",
      "organizer": "Berkeley E-Hub",
      "date": "2026-08-27",
      "time": "See event page",
      "location": "Berkeley E-Hub",
      "description": "Start Something @ the eHub Open House",
      "url": "https://ehub.berkeley.edu/events/",
      "tags": [
        "Entrepreneurship"
      ]
    }
  ],
  "sources": [
    {
      "title": "Berkeley E-Hub Events",
      "uri": "https://ehub.berkeley.edu/events/"
    }
  ],
  "lastUpdated": 1772462650399
}