{
  "generated_at": "2026-04-19T14:39:40.106Z",
  "total_events": 1061,
  "duplicates_removed": 266,
  "past_events_filtered": 3118,
  "invalid_events_filtered": 3,
  "sources": [
    {
      "name": "livewhale",
      "ok": true,
      "count": 978,
      "duration_ms": 2898,
      "fetched_at": "2026-04-19T14:38:43.476Z"
    },
    {
      "name": "callink",
      "ok": true,
      "count": 10,
      "duration_ms": 553,
      "fetched_at": "2026-04-19T14:38:43.512Z"
    },
    {
      "name": "cal_performances",
      "ok": true,
      "count": 7,
      "duration_ms": 11257,
      "fetched_at": "2026-04-19T14:38:43.514Z"
    },
    {
      "name": "calbears",
      "ok": true,
      "count": 89,
      "duration_ms": 544,
      "fetched_at": "2026-04-19T14:38:43.516Z"
    },
    {
      "name": "bampfa",
      "ok": true,
      "count": 72,
      "duration_ms": 56370,
      "fetched_at": "2026-04-19T14:38:43.518Z"
    },
    {
      "name": "haas",
      "ok": true,
      "count": 25,
      "duration_ms": 2363,
      "fetched_at": "2026-04-19T14:38:43.519Z"
    },
    {
      "name": "berkeley_law",
      "ok": true,
      "count": 53,
      "duration_ms": 2388,
      "fetched_at": "2026-04-19T14:38:43.521Z"
    },
    {
      "name": "simons",
      "ok": true,
      "count": 44,
      "duration_ms": 17627,
      "fetched_at": "2026-04-19T14:38:43.522Z"
    },
    {
      "name": "ehub",
      "ok": true,
      "count": 37,
      "duration_ms": 736,
      "fetched_at": "2026-04-19T14:38:43.523Z"
    },
    {
      "name": "gemini",
      "ok": true,
      "count": 12,
      "duration_ms": 47167,
      "fetched_at": "2026-04-19T14:38:43.525Z"
    }
  ],
  "fallback_used": false,
  "degraded": false,
  "last_good_used": 0,
  "fallback_sources": [],
  "degraded_sources": []
}